ShadowPT/__init__.py
ShadowPT/args_.py
ShadowPT/exemplo.txt
ShadowPT/moradas.py
ShadowPT/nomes_.py
ShadowPT/utils.py
ShadowPT/conf/config.json
ShadowPT/dados/apelidos.txt
ShadowPT/dados/moradas.txt
ShadowPT/dados/nomes.pdf
ShadowPT/dados/nomes.txt
ShadowPT/dados/moradas_model/config.cfg
ShadowPT/dados/moradas_model/meta.json
ShadowPT/dados/moradas_model/tokenizer
ShadowPT/dados/moradas_model/ner/cfg
ShadowPT/dados/moradas_model/ner/model
ShadowPT/dados/moradas_model/ner/moves
ShadowPT/dados/moradas_model/vocab/key2row
ShadowPT/dados/moradas_model/vocab/lookups.bin
ShadowPT/dados/moradas_model/vocab/strings.json
ShadowPT/dados/moradas_model/vocab/vectors
ShadowPT/dados/moradas_model/vocab/vectors.cfg
shadowpt-0.3.dist-info/entry_points.txt
shadowpt-0.3.dist-info/LICENSE
shadowpt-0.3.dist-info/WHEEL
shadowpt-0.3.dist-info/METADATA
shadowpt-0.3.dist-info/RECORD
