Metadata-Version: 2.1
Name: ShadowPT
Version: 0.3
Summary: Modulo que, dado um determinado texto, anónimiza a sua informação.
Author-email: gcf <pg50398@alunos.uminho.pt>, hjfa <pg50414@alunos.uminho.pt>
Classifier: License :: OSI Approved :: MIT License
Requires-Dist: requests
Requires-Dist: bs4
Requires-Dist: argparse
Requires-Dist: spacy
Project-URL: Home, https://github.com/Miyagi61/SPLN-TP2
